maldinio_ai/__init__.py
maldinio_ai/api/__init__.py
maldinio_ai/api/api_key_loader.py
maldinio_ai/memory_management/__init__.py
maldinio_ai/memory_management/memory_manager.py
maldinio_ai/nlp/__init__.py
maldinio_ai/nlp/nlp_client.py
maldinio_ai/nlp/nlp_processor.py
maldinio_ai/prompt/__init__.py
maldinio_ai/prompt/prompt_context.py
maldinio_ai/prompt/prompt_generator.py
maldinio_ai/prompt/response_processor.py
maldinio_ai/tests/__init__.py
maldinio_ai/tests/test_app.py
maldinio_ai/tests/test_nlp_client.py
maldinio_ai/tools/__init__.py
maldinio_ai/tools/create_project_folder.py
maldinio_ai/tools/load_project.py
maldinio_ai/utils/__init__.py
maldinio_ai/utils/helpers.py
maldinio_ai/utils/json_utils.py
maldinio_ai/utils/verification_utils.py
maldinio_ai-0.1.8.dist-info/LICENSE
maldinio_ai-0.1.8.dist-info/METADATA
maldinio_ai-0.1.8.dist-info/WHEEL
maldinio_ai-0.1.8.dist-info/top_level.txt
maldinio_ai-0.1.8.dist-info/RECORD
